sella/internal.py
sella/__init__.py
sella/force_match.cpython-311-darwin.so
sella/linalg.py
sella/hessian_update.py
sella/py.typed
sella/samd.py
sella/peswrapper.py
sella/eigensolvers.py
sella/optimize/optimize.py
sella/optimize/stepper.py
sella/optimize/irc.py
sella/optimize/__init__.py
sella/optimize/restricted_step.py
sella/utilities/math.cpython-311-darwin.so
sella/utilities/__init__.py
sella/utilities/blas.cpython-311-darwin.so
Sella-2.3.5.dist-info/RECORD
Sella-2.3.5.dist-info/LICENSE
Sella-2.3.5.dist-info/WHEEL
Sella-2.3.5.dist-info/top_level.txt
Sella-2.3.5.dist-info/METADATA
