Metadata-Version: 2.1
Name: Sella
Version: 2.3.5
Author: Eric Hermes
Author-email: ehermes@sandia.gov
Classifier: Development Status :: 4 - Beta
Classifier: Environment :: Console
Classifier: Intended Audience :: Science/Research
Classifier: License :: OSI Approved :: GNU Lesser General Public License v3 (LGPLv3)
Classifier: Natural Language :: English
Classifier: Operating System :: OS Independent
Classifier: Programming Language :: Python :: 3.8
Classifier: Programming Language :: Cython
Classifier: Topic :: Scientific/Engineering :: Chemistry
Classifier: Topic :: Scientific/Engineering :: Mathematics
Classifier: Topic :: Scientific/Engineering :: Physics
Requires-Python: >=3.8
License-File: LICENSE
Requires-Dist: numpy >=1.14.0
Requires-Dist: scipy >=1.1.0
Requires-Dist: ase >=3.18.0
Requires-Dist: jax >=0.4.20
Requires-Dist: jaxlib >=0.4.20
